{"id":"e861f006-189a-4de3-8c24-3ff7ebb85b5d","timestamp":1749308497289,"matcher":{"static":{},"wildcard":{},"dynamic":{}},"prerendered":["/","/ja","/contact","/ja/contact","/ja/game/survey","/game/survey","/tool","/game","/ja/game","/tool/browsergame","/tool/asset","/tool/opensourcegame","/ja/tool","/ja/tool/browsergame","/ja/tool/asset","/ja/tool/opensourcegame","/ja/article","/article","/tool/framework","/ja/tool/framework","/article/ah-aloud","/ja/article/ah-aloud","/article/ces-result","/ja/article/ces-result"]}